morphers/__init__.py
morphers/nn.py
morphers/backends/polars/__init__.py
morphers/backends/polars/categorical.py
morphers/backends/polars/continuous.py
morphers/base/base.py
morphers/base/helpers.py
morphers/morphers/__init__.py
morphers/morphers/categorical.py
morphers/morphers/continuous.py
morphers-0.1.2.dist-info/METADATA
morphers-0.1.2.dist-info/WHEEL
morphers-0.1.2.dist-info/licenses/LICENSE
morphers-0.1.2.dist-info/RECORD
