Metadata-Version: 2.3
Name: morphers
Version: 0.1.2
Summary: Tools to handle data transformations for tabular-ish deep learning models.
Project-URL: Homepage, https://github.com/play4honor/morphers/tree/main
Project-URL: Issues, https://github.com/play4honor/morphers/issues
License: MIT License
License-File: LICENSE
Classifier: License :: OSI Approved :: MIT License
Classifier: Operating System :: OS Independent
Classifier: Programming Language :: Python :: 3
Requires-Python: >=3.10
Requires-Dist: numpy>=1.26
Requires-Dist: polars>=0.20
Requires-Dist: torch>=2.0
